xevo/__init__.py
xevo/crossevo.py
xevo/eobj.py
xevo/eobjplus.py
xevo/erun.py
xevo/erunplus.py
xevo/evo.py
xevo/mob.py
xevo/oobj.py
xevo/phobia.py
xevo/pion.py
xevo/quickmut.py
xevo/objects/__init__.py
xevo/objects/bitflip.py
xevo/objects/dualflip.py
xevo/objects/gotozero.py
xevo/objects/oion.py
xevo/objects/pion.py
xevo/objects/pionplus.py
xevo/optimizers/__init__.py
xevo/optimizers/morthoevo.py
xevo/optimizers/orthoevo.py
xevo/optimizers/trajmute.py
xevo/optimizers/trajmuteplus.py
xevo/optimizers/trivmute.py
xevo/optimizers/trivmutetraj.py
xevo-0.52.dist-info/LICENSE
xevo-0.52.dist-info/METADATA
xevo-0.52.dist-info/WHEEL
xevo-0.52.dist-info/top_level.txt
xevo-0.52.dist-info/RECORD
