Metadata-Version: 2.1
Name: xevo
Version: 0.52
Summary: A simple polymorph evolutionary class system
Home-page: https://github.com/psorus/xevo/
Author: Simon Klüttermann
Author-email: Simon.Kluettermann@gmx.de
License: UNKNOWN
Download-URL: https://github.com/psorus/xevo/archive/0.52.tar.gz
Platform: UNKNOWN
Classifier: Programming Language :: Python :: 3
Classifier: License :: OSI Approved :: MIT License
Classifier: Operating System :: OS Independent
Requires-Python: >=3.6
Requires-Dist: numpy
Requires-Dist: matplotlib
